pyres/__init__.py
pyres/mesh_tools.py
pyres/mesh_utils.py
pyres/plot_utils.py
pyres/pyres_utils.py
pyres/r2_tools.py
pyres/r3_tools.py
pyresistivity-1.0.0.dist-info/DESCRIPTION.rst
pyresistivity-1.0.0.dist-info/METADATA
pyresistivity-1.0.0.dist-info/RECORD
pyresistivity-1.0.0.dist-info/WHEEL
pyresistivity-1.0.0.dist-info/metadata.json
pyresistivity-1.0.0.dist-info/top_level.txt
