Metadata-Version: 2.0
Name: pyresistivity
Version: 1.0.0
Summary: pyres is a Python package to create, run, and post-process R2 electrical resistivity forward and inverse models.
Home-page: https://github.com/kbefus/pyres/
Author: Kevin M. Befus
Author-email: kbefus@uwyo.edu
License: New BSD
Keywords: geophysics resistivity inversion
Platform: Windows
Platform: Mac OS-X
Platform: Unix
Requires-Dist: numpy (>=1.7)
